cleandev_framework
